[
  {
    "name": "Tranquil Retreat",
    "cabinType": ["RELAXATION"],
    "numRooms": 3,
    "maxCapacity": 5,
    "regularPrice": 180.0,
    "discount": 10.0,
    "description": "A peaceful retreat designed for ultimate relaxation, nestled in serene surroundings.",
    "image": "https://images.pexels.com/photos/2373201/pexels-photo-2373201.jpeg?auto=compress&cs=tinysrgb&w=1260&h=750&dpr=2",
    "country": "Switzerland",
    "city": "Zurich",
    "latitude": 47.3769,
    "longitude": 8.5417,
    "features": ["WIFI", "PARKING", "HEATING", "TERRACE"],
    "userId": "3b661f43-cc48-4d63-a8ee-cf11f517d98b"
  },
  {
    "name": "Peaceful Sanctuary",
    "cabinType": ["RELAXATION"],
    "numRooms": 2,
    "maxCapacity": 4,
    "regularPrice": 160.0,
    "discount": 12.0,
    "description": "A serene sanctuary perfect for escaping the hustle and bustle of everyday life.",
    "image": "https://images.pexels.com/photos/4023389/pexels-photo-4023389.jpeg?auto=compress&cs=tinysrgb&w=1260&h=750&dpr=2",
    "country": "Norway",
    "city": "Oslo",
    "latitude": 59.9139,
    "longitude": 10.7522,
    "features": ["WIFI", "PARKING", "TERRACE", "HEATING", "BREAKFAST_INCLUDED"],
    "userId": "3b661f43-cc48-4d63-a8ee-cf11f517d98b"
  },
  {
    "name": "Zen Escape",
    "cabinType": ["RELAXATION"],
    "numRooms": 4,
    "maxCapacity": 6,
    "regularPrice": 190.0,
    "discount": 15.0,
    "description": "A Zen-inspired cabin with calming interior design and a peaceful environment.",
    "image": "https://images.pexels.com/photos/14012236/pexels-photo-14012236.jpeg?auto=compress&cs=tinysrgb&w=1260&h=750&dpr=2",
    "country": "Japan",
    "city": "Kyoto",
    "latitude": 35.0116,
    "longitude": 135.7681,
    "features": ["WIFI", "PARKING", "TERRACE", "HEATING"],
    "userId": "3b661f43-cc48-4d63-a8ee-cf11f517d98b"
  },
  {
    "name": "Harmony Haven",
    "cabinType": ["RELAXATION"],
    "numRooms": 2,
    "maxCapacity": 3,
    "regularPrice": 170.0,
    "discount": 10.0,
    "description": "A haven designed to bring peace and harmony to your life, surrounded by nature's beauty.",
    "image": "https://images.pexels.com/photos/2363807/pexels-photo-2363807.jpeg?auto=compress&cs=tinysrgb&w=1260&h=750&dpr=2",
    "country": "Canada",
    "city": "Vancouver",
    "latitude": 49.2827,
    "longitude": -123.1207,
    "features": ["WIFI", "PARKING", "HEATING", "TERRACE"],
    "userId": "3b661f43-cc48-4d63-a8ee-cf11f517d98b"
  },
  {
    "name": "Cozy Hideaway",
    "cabinType": ["RELAXATION"],
    "numRooms": 3,
    "maxCapacity": 5,
    "regularPrice": 160.0,
    "discount": 5.0,
    "description": "A cozy hideaway designed for comfort and relaxation, perfect for a peaceful weekend.",
    "image": "https://images.pexels.com/photos/2096983/pexels-photo-2096983.jpeg?auto=compress&cs=tinysrgb&w=1260&h=750&dpr=2",
    "country": "France",
    "city": "Paris",
    "latitude": 48.8566,
    "longitude": 2.3522,
    "features": ["WIFI", "PARKING", "HEATING"],
    "userId": "3b661f43-cc48-4d63-a8ee-cf11f517d98b"
  },
  {
    "name": "Breeze Cabin",
    "cabinType": ["RELAXATION"],
    "numRooms": 1,
    "maxCapacity": 2,
    "regularPrice": 140.0,
    "discount": 8.0,
    "description": "A small, intimate cabin designed for two, offering a peaceful space to unwind.",
    "image": "https://images.pexels.com/photos/2057610/pexels-photo-2057610.jpeg?auto=compress&cs=tinysrgb&w=1260&h=750&dpr=2",
    "country": "Italy",
    "city": "Rome",
    "latitude": 41.9028,
    "longitude": 12.4964,
    "features": ["WIFI", "PARKING", "HEATING"],
    "userId": "3b661f43-cc48-4d63-a8ee-cf11f517d98b"
  },
  {
    "name": "Solitude Sanctuary",
    "cabinType": ["RELAXATION"],
    "numRooms": 5,
    "maxCapacity": 7,
    "regularPrice": 250.0,
    "discount": 25.0,
    "description": "A sanctuary where you can experience complete solitude, tranquility, and serenity.",
    "image": "https://images.pexels.com/photos/3516149/pexels-photo-3516149.jpeg?auto=compress&cs=tinysrgb&w=1600",
    "country": "New Zealand",
    "city": "Wellington",
    "latitude": -41.2867,
    "longitude": 174.7762,
    "features": ["WIFI", "PARKING", "TERRACE", "HEATING", "RECEPTION_24H"],
    "userId": "3b661f43-cc48-4d63-a8ee-cf11f517d98b"
  },
  {
    "name": "Mountain Retreat",
    "cabinType": ["RELAXATION"],
    "numRooms": 4,
    "maxCapacity": 6,
    "regularPrice": 230.0,
    "discount": 30.0,
    "description": "A relaxing retreat in the mountains with spectacular views and outdoor tranquility.",
    "image": "https://images.pexels.com/photos/11493028/pexels-photo-11493028.jpeg?auto=compress&cs=tinysrgb&w=1260&h=750&dpr=2",
    "country": "USA",
    "city": "Colorado",
    "latitude": 39.5501,
    "longitude": -105.7821,
    "features": ["WIFI", "PARKING", "HEATING", "TERRACE", "BAR"],
    "userId": "3b661f43-cc48-4d63-a8ee-cf11f517d98b"
  },
  {
    "name": "Serenity Cove",
    "cabinType": ["RELAXATION"],
    "numRooms": 3,
    "maxCapacity": 5,
    "regularPrice": 820.0,
    "discount": 18.0,
    "description": "A peaceful cove to relax and rejuvenate with views of the serene coastline.",
    "image": "https://images.pexels.com/photos/2972890/pexels-photo-2972890.jpeg?auto=compress&cs=tinysrgb&w=1260&h=750&dpr=2",
    "country": "Mexico",
    "city": "Tulum",
    "latitude": 20.2113,
    "longitude": -87.4699,
    "features": [
      "WIFI",
      "PARKING",
      "TERRACE",
      "HEATING",
      "BREAKFAST_INCLUDED",
      "NON_SMOKING",
      "DISABLED_ACCESS",
      "RECEPTION_24H"
    ],
    "userId": "3b661f43-cc48-4d63-a8ee-cf11f517d98b"
  }
]
